MANIFEST.in
README.md
setup.cfg
setup.py
TOPSIS_Rahet_101803173/TOPSIS.py
TOPSIS_Rahet_101803173.egg-info/PKG-INFO
TOPSIS_Rahet_101803173.egg-info/SOURCES.txt
TOPSIS_Rahet_101803173.egg-info/dependency_links.txt
TOPSIS_Rahet_101803173.egg-info/entry_points.txt
TOPSIS_Rahet_101803173.egg-info/requires.txt
TOPSIS_Rahet_101803173.egg-info/top_level.txt