Metadata-Version: 2.1
Name: TOPSIS-Rahet-101803173
Version: 1.1
Summary: A Python package implementing TOPSIS technique.
Home-page: UNKNOWN
Author: Rahet Tuteja
Author-email: rahettuteja@gmail.com
License: MIT
Platform: UNKNOWN
Classifier: License :: OSI Approved :: MIT License
Classifier: Programming Language :: Python :: 3
Classifier: Programming Language :: Python :: 3.7
